{"mutatedEntities":{"CREATE":[{"typeName":"AtlasGlossary","attributes":{"popularityScore":1.17549435e-38,"lastSyncRunAt":0,"assetDbtJobLastRunHasSourcesGenerated":false,"__hasLineage":false,"sourceQueryComputeCostRecordList":[],"assetDbtJobLastRunHasDocsGenerated":false,"adminUsers":[],"lastRowChangedAt":0,"sourceReadRecentUserList":[],"assetDbtJobLastRunUpdatedAt":0,"ownerGroups":[],"sourceUpdatedAt":0,"assetDbtJobLastRunArtifactsSaved":false,"isEditable":true,"sourceReadCount":0,"sourceReadExpensiveQueryRecordList":[],"announcementUpdatedAt":0,"assetDbtJobLastRunStartedAt":0,"isDiscoverable":true,"sourceReadTopUserRecordList":[],"sourceCreatedAt":0,"assetDbtJobLastRunDequedAt":0,"viewerUsers":[],"assetDbtTags":[],"viewScore":1.17549435e-38,"sourceReadTopUserList":[],"adminRoles":[],"sourceReadSlowQueryRecordList":[],"adminGroups":[],"qualifiedName":"7OLUaDHVX3HV8yTINNYG7","sourceQueryComputeCostList":[],"assetDbtJobLastRunCreatedAt":0,"assetDbtJobNextRun":0,"assetDbtJobLastRunNotificationsSent":false,"sourceReadRecentUserRecordList":[],"sourceReadPopularQueryRecordList":[],"sourceTotalCost":0,"sourceReadUserCount":0,"sourceLastReadAt":0,"name":"SravyaTest1","certificateUpdatedAt":0,"viewerGroups":[],"assetDbtJobLastRun":0,"ownerUsers":[]},"guid":"a9c5fb7e-ccd2-4bba-b986-a40808f128c5","status":"ACTIVE","displayText":"SravyaTest1","classificationNames":[],"classifications":[],"meaningNames":[],"meanings":[],"isIncomplete":false,"labels":[],"createdBy":"service-account-apikey-d3c62f78-e9be-4afb-9590-8988c8030670","updatedBy":"service-account-apikey-d3c62f78-e9be-4afb-9590-8988c8030670","createTime":1675250234691,"updateTime":1675250234691}]},"guidAssignments":{"-10584510932596":"a9c5fb7e-ccd2-4bba-b986-a40808f128c5"}}
